README.md
setup.py
pymochad_mqtt/__init__.py
pymochad_mqtt/controller.py
pymochad_mqtt/parser.py
pymochad_mqtt.egg-info/PKG-INFO
pymochad_mqtt.egg-info/SOURCES.txt
pymochad_mqtt.egg-info/dependency_links.txt
pymochad_mqtt.egg-info/top_level.txt