Metadata-Version: 2.1
Name: pymochad-mqtt
Version: 0.8.7
Summary: Mochad wrapper in Python with mqtt interface
Home-page: https://github.com/aosadchyy/pymochad_mqtt
Author: Alex Osadchyy
Author-email: aosadchyy@outlook.com
License: UNKNOWN
Platform: UNKNOWN
Classifier: Programming Language :: Python :: 3
Classifier: License :: OSI Approved :: GNU General Public License v3 (GPLv3)
Classifier: Operating System :: OS Independent
